snec/__init__.py
snec/test_api.py
snec-0.1.0.dist-info/WHEEL
snec-0.1.0.dist-info/METADATA
snec-0.1.0.dist-info/RECORD
